<Properties StartupConfiguration="{77DB1EC8-3639-4408-B1A3-BAC8A7968AC4}|Default">
  <MonoDevelop.Ide.Workbench />
  <MonoDevelop.Ide.ItemProperties.fms PreferredExecutionTarget="MonoDevelop.Default" />
  <MonoDevelop.Ide.DebuggingService.PinnedWatches>
    <Watch file="../../../Controllers/EmployeeController.cs" line="128" offsetX="329" offsetY="1905" expression="ModelState" liveUpdate="False" />
    <Watch file="../../../Controllers/DashboardController.cs" line="28" offsetX="648" offsetY="405" expression="string" liveUpdate="False" />
  </MonoDevelop.Ide.DebuggingService.PinnedWatches>
  <MonoDevelop.Ide.Workspace ActiveConfiguration="Debug" />
  <MonoDevelop.Ide.DebuggingService.Breakpoints>
    <BreakpointStore />
  </MonoDevelop.Ide.DebuggingService.Breakpoints>
  <MultiItemStartupConfigurations />
</Properties>